includes/__init__.py
includes/scanning.py
includes/url_reader.py
includes/write_and_read.py
utils/__init__.py
utils/banner.py
utils/internet_check.py
bharath_openredirect-0.1.0.dist-info/LICENSE.txt
bharath_openredirect-0.1.0.dist-info/METADATA
bharath_openredirect-0.1.0.dist-info/WHEEL
bharath_openredirect-0.1.0.dist-info/entry_points.txt
bharath_openredirect-0.1.0.dist-info/top_level.txt
bharath_openredirect-0.1.0.dist-info/RECORD
