Metadata-Version: 2.1
Name: bharath_openredirect
Version: 0.1.0
Summary: A tool to identify potential open redirect vulnerabilities in URLs.
Home-page: 
Author: Y
Author-email: your.email@example.com
Classifier: Programming Language :: Python :: 3
Classifier: License :: OSI Approved :: MIT License
Classifier: Operating System :: OS Independent
Requires-Python: >=3.6
License-File: LICENSE.txt
Requires-Dist: requests
